README.md
README.rst
setup.cfg
setup.py
sklearn_rri/__init__.py
sklearn_rri/_version.py
sklearn_rri/rri.py
sklearn_rri.egg-info/PKG-INFO
sklearn_rri.egg-info/SOURCES.txt
sklearn_rri.egg-info/dependency_links.txt
sklearn_rri.egg-info/requires.txt
sklearn_rri.egg-info/top_level.txt
sklearn_rri/tests/__init__.py
sklearn_rri/tests/test_rri.py