Metadata-Version: 1.1
Name: sklearn-rri
Version: 0.1.0
Summary: scikit-learn compatible classifier based on RRI
Home-page: https://github.com/cmick/sklearn-rri
Author: Michal Ciesielczyk
Author-email: michal.ciesielczyk@put.poznan.pl
License: BSD
Platform: UNKNOWN
Classifier: Development Status :: 3 - Alpha
Classifier: Topic :: Scientific/Engineering
Classifier: Topic :: Software Development
Classifier: Intended Audience :: Developers
Classifier: Intended Audience :: Science/Research
Classifier: License :: OSI Approved :: BSD License
Classifier: Operating System :: OS Independent
Classifier: Programming Language :: Python :: 2.7
Classifier: Programming Language :: Python :: 3.4
Classifier: Programming Language :: Python :: 3.5
Classifier: Programming Language :: Python :: 3.6
